yapomo/__init__.py
yapomo/yapomo.py
yapomo-1.1.4.dist-info/METADATA
yapomo-1.1.4.dist-info/WHEEL
yapomo-1.1.4.dist-info/entry_points.txt
yapomo-1.1.4.dist-info/licenses/LICENSE
yapomo-1.1.4.dist-info/RECORD
