Metadata-Version: 2.1
Name: yapomo
Version: 1.1.4
Summary: yapomo - Yet Another Pomodoro Timer
Author-email: João Dias <joaodias@users.sourceforge.net>
License: GNU GENERAL PUBLIC LICENSE
License-File: LICENSE
Keywords: pomodoro,timer,tkinter
Classifier: Development Status :: 5 - Production/Stable
Classifier: Intended Audience :: Developers
Classifier: License :: OSI Approved :: GNU General Public License v3 or later (GPLv3+)
Classifier: Operating System :: OS Independent
Classifier: Programming Language :: Python :: 3
Classifier: Topic :: Office/Business :: Scheduling
Requires-Python: >=3.5
